apip/__init__.py
apip/client.py
apip/package.py
apip/abc/__init__.py
apip/abc/basepackage.py
apip/abc/errors.py
apip/abc/installer.py
apip-0.2.0.dist-info/LICENSE
apip-0.2.0.dist-info/METADATA
apip-0.2.0.dist-info/WHEEL
apip-0.2.0.dist-info/top_level.txt
apip-0.2.0.dist-info/RECORD
