Metadata-Version: 2.1
Name: apip
Version: 0.2.0
Summary: An asynchronous api wrapper for pip!
Home-page: https://github.com/SomeHybrid/apip
License: MIT
Project-URL: Documentation, https://apip.readthedocs.io/
Project-URL: Homepage, https://github.com/SomeHybrid/apip
Project-URL: Issue Tracker, https://github.com/SomeHybrid/apip/issues
Keywords: pip,python,pypi
Classifier: Environment :: Console
Classifier: Programming Language :: Python :: 3
Classifier: Programming Language :: Python :: 3.7
License-File: LICENSE
Requires-Dist: aiohttp (>=3.8.1)
